aws_ssm_juggle/__init__.py
aws_ssm_juggle/ec2.py
aws_ssm_juggle/ecs.py
aws_ssm_juggle-26.1.0.dist-info/METADATA
aws_ssm_juggle-26.1.0.dist-info/WHEEL
aws_ssm_juggle-26.1.0.dist-info/entry_points.txt
aws_ssm_juggle-26.1.0.dist-info/licenses/LICENSE
aws_ssm_juggle-26.1.0.dist-info/RECORD
