Metadata-Version: 2.4
Name: aws-ssm-juggle
Version: 26.1.0
Summary: AWS SSM tool for ECS/EC2 (Shell, SSH/SCP, Port Forwarding, ...)
License: MIT
License-File: LICENSE
Author: Stefan Heitmüller
Author-email: stefan.heitmueller@gmx.com
Classifier: License :: OSI Approved :: MIT License
Classifier: Programming Language :: Python :: 2
Classifier: Programming Language :: Python :: 2.7
Classifier: Programming Language :: Python :: 3
Classifier: Programming Language :: Python :: 3.4
Classifier: Programming Language :: Python :: 3.5
Classifier: Programming Language :: Python :: 3.6
Classifier: Programming Language :: Python :: 3.7
Classifier: Programming Language :: Python :: 3.8
Classifier: Programming Language :: Python :: 3.9
Classifier: Programming Language :: Python :: 3.10
Classifier: Programming Language :: Python :: 3.11
Classifier: Programming Language :: Python :: 3.12
Classifier: Programming Language :: Python :: 3.13
Classifier: Programming Language :: Python :: 3.14
Requires-Dist: InquirerPy
Requires-Dist: boto3
Requires-Dist: configargparse
Requires-Dist: diskcache
Requires-Dist: munch
Requires-Dist: psutil
Requires-Dist: shtab
Project-URL: Repository, https://github.com/morph027/aws-ssm-juggle
